py_basic_ses/__init__.py
py_basic_ses/emailing.py
py_basic_ses/entry.py
py_basic_ses/exceptions.py
py_basic_ses-2.0.1.dist-info/LICENSE
py_basic_ses-2.0.1.dist-info/METADATA
py_basic_ses-2.0.1.dist-info/WHEEL
py_basic_ses-2.0.1.dist-info/entry_points.txt
py_basic_ses-2.0.1.dist-info/top_level.txt
py_basic_ses-2.0.1.dist-info/RECORD
