Metadata-Version: 2.1
Name: py-basic-ses
Version: 2.0.1
Summary: py-basic-ses provides a command line application and library to send emails via Amazon Web Services' Simple Email Service, or AWS SES, API by leveraging the boto3 library.
Home-page: https://github.com/shinyshoes404/py-basic-ses
Author: shinyshoes
Author-email: shinyshoes404@protonmail.com
License: MIT License
Classifier: License :: OSI Approved :: MIT License
Classifier: Operating System :: Microsoft :: Windows
Classifier: Operating System :: POSIX :: Linux
Classifier: Programming Language :: Python :: 3.8
Classifier: Programming Language :: Python :: 3.9
Classifier: Programming Language :: Python :: 3.10
Classifier: Programming Language :: Python :: 3.11
Classifier: Programming Language :: Python :: 3.12
Requires-Python: >=3.8,!=3.13.*
License-File: LICENSE
Requires-Dist: boto3 (>=1.17)
Requires-Dist: click
Provides-Extra: dev
Requires-Dist: coverage ; extra == 'dev'
Requires-Dist: mock ; extra == 'dev'
